t3f/__init__.py
t3f/approximate.py
t3f/approximate_test.py
t3f/autodiff.py
t3f/autodiff_test.py
t3f/batch_ops.py
t3f/batch_ops_test.py
t3f/decompositions.py
t3f/decompositions_test.py
t3f/examples_tests.py
t3f/initializers.py
t3f/initializers_test.py
t3f/kronecker.py
t3f/kronecker_test.py
t3f/nn.py
t3f/nn_test.py
t3f/ops.py
t3f/ops_test.py
t3f/regularizers.py
t3f/riemannian.py
t3f/riemannian_test.py
t3f/shapes.py
t3f/shapes_test.py
t3f/tensor_train.py
t3f/tensor_train_base.py
t3f/tensor_train_batch.py
t3f/tensor_train_batch_test.py
t3f/tensor_train_test.py
t3f/utils.py
t3f/utils_test.py
t3f/variables.py
t3f/variables_test.py
t3f-1.1.0.dist-info/LICENSE
t3f-1.1.0.dist-info/METADATA
t3f-1.1.0.dist-info/WHEEL
t3f-1.1.0.dist-info/top_level.txt
t3f-1.1.0.dist-info/RECORD
