Metadata-Version: 2.1
Name: t3f
Version: 1.1.0
Summary: Tensor Train decomposition on TensorFlow
Home-page: https://github.com/Bihaqo/t3f
Author: Alexander Novikov
Author-email: sasha.v.novikov@gmail.com
License: MIT
Platform: UNKNOWN
Requires-Dist: numpy
